ontonaut/__init__.py
ontonaut/chatbot.py
ontonaut/editor.py
ontonaut/executors.py
ontonaut/handlers.py
ontonaut/py.typed
ontonaut/static/chatbot.css
ontonaut/static/chatbot.js
ontonaut/static/editor.css
ontonaut/static/editor.js
ontonaut-0.1.0.dist-info/METADATA
ontonaut-0.1.0.dist-info/WHEEL
ontonaut-0.1.0.dist-info/licenses/LICENSE
ontonaut-0.1.0.dist-info/RECORD
