Metadata-Version: 2.4
Name: ontonaut
Version: 0.1.0
Summary: Customizable code editor widget for marimo with pluggable execution backends
Project-URL: Homepage, https://github.com/yourusername/ontonaut
Project-URL: Documentation, https://github.com/yourusername/ontonaut#readme
Project-URL: Repository, https://github.com/yourusername/ontonaut
Project-URL: Issues, https://github.com/yourusername/ontonaut/issues
Author-email: Ashley Cottrell <your.email@example.com>
License: MIT
License-File: LICENSE
Keywords: anywidget,code-editor,jupyter,marimo,notebook,widget
Classifier: Development Status :: 3 - Alpha
Classifier: Framework :: Jupyter
Classifier: Intended Audience :: Developers
Classifier: License :: OSI Approved :: MIT License
Classifier: Programming Language :: Python :: 3
Classifier: Programming Language :: Python :: 3.9
Classifier: Programming Language :: Python :: 3.10
Classifier: Programming Language :: Python :: 3.11
Classifier: Programming Language :: Python :: 3.12
Classifier: Topic :: Software Development :: Code Generators
Classifier: Topic :: Software Development :: Interpreters
Requires-Python: >=3.9
Requires-Dist: anywidget>=0.9.0
Requires-Dist: marimo>=0.1.0
Requires-Dist: python-dotenv>=1.0.0
Provides-Extra: all
Requires-Dist: anthropic>=0.18.0; extra == 'all'
Requires-Dist: openai>=1.0.0; extra == 'all'
Provides-Extra: anthropic
Requires-Dist: anthropic>=0.18.0; extra == 'anthropic'
Provides-Extra: dev
Requires-Dist: black>=24.0.0; extra == 'dev'
Requires-Dist: mypy>=1.8.0; extra == 'dev'
Requires-Dist: pre-commit>=3.6.0; extra == 'dev'
Requires-Dist: pytest-asyncio>=0.23.0; extra == 'dev'
Requires-Dist: pytest-cov>=4.1.0; extra == 'dev'
Requires-Dist: pytest>=8.0.0; extra == 'dev'
Requires-Dist: ruff>=0.1.0; extra == 'dev'
Provides-Extra: openai
Requires-Dist: openai>=1.0.0; extra == 'openai'
